julee/__init__.py
julee/worker.py
julee/api/__init__.py
julee/api/app.py
julee/api/dependencies.py
julee/api/requests.py
julee/api/responses.py
julee/api/routers/__init__.py
julee/api/routers/assembly_specifications.py
julee/api/routers/documents.py
julee/api/routers/knowledge_service_configs.py
julee/api/routers/knowledge_service_queries.py
julee/api/routers/system.py
julee/api/routers/workflows.py
julee/api/services/__init__.py
julee/api/services/system_initialization.py
julee/api/tests/__init__.py
julee/api/tests/test_app.py
julee/api/tests/test_dependencies.py
julee/api/tests/test_requests.py
julee/api/tests/routers/__init__.py
julee/api/tests/routers/test_assembly_specifications.py
julee/api/tests/routers/test_documents.py
julee/api/tests/routers/test_knowledge_service_configs.py
julee/api/tests/routers/test_knowledge_service_queries.py
julee/api/tests/routers/test_system.py
julee/api/tests/routers/test_workflows.py
julee/contrib/__init__.py
julee/contrib/polling/__init__.py
julee/contrib/polling/apps/__init__.py
julee/contrib/polling/apps/worker/__init__.py
julee/contrib/polling/apps/worker/pipelines.py
julee/contrib/polling/domain/__init__.py
julee/contrib/polling/domain/models/__init__.py
julee/contrib/polling/domain/models/polling_config.py
julee/contrib/polling/domain/services/__init__.py
julee/contrib/polling/domain/services/poller.py
julee/contrib/polling/infrastructure/__init__.py
julee/contrib/polling/infrastructure/services/__init__.py
julee/contrib/polling/infrastructure/services/polling/__init__.py
julee/contrib/polling/infrastructure/services/polling/http/__init__.py
julee/contrib/polling/infrastructure/services/polling/http/http_poller_service.py
julee/contrib/polling/infrastructure/temporal/__init__.py
julee/contrib/polling/infrastructure/temporal/activities.py
julee/contrib/polling/infrastructure/temporal/activity_names.py
julee/contrib/polling/infrastructure/temporal/manager.py
julee/contrib/polling/infrastructure/temporal/proxies.py
julee-0.1.7.dist-info/licenses/LICENSE
julee-0.1.7.dist-info/METADATA
julee-0.1.7.dist-info/WHEEL
julee-0.1.7.dist-info/top_level.txt
julee-0.1.7.dist-info/RECORD
