Metadata-Version: 2.4
Name: julee
Version: 0.1.7
Summary: Julee - Clean architecture for accountable and transparent digital supply chains
Author-email: Pyx Industries <chris@pyx.io>
License: GPL-3.0
Project-URL: Homepage, https://github.com/pyx-industries/julee
Project-URL: Repository, https://github.com/pyx-industries/julee
Project-URL: Documentation, https://github.com/pyx-industries/julee#readme
Project-URL: Issues, https://github.com/pyx-industries/julee/issues
Keywords: temporal,workflow,document-processing,ai,supply-chain
Classifier: Development Status :: 3 - Alpha
Classifier: Intended Audience :: Developers
Classifier: License :: OSI Approved :: GNU General Public License v3 (GPLv3)
Classifier: Programming Language :: Python :: 3
Classifier: Programming Language :: Python :: 3.11
Classifier: Programming Language :: Python :: 3.12
Classifier: Topic :: Software Development :: Libraries :: Python Modules
Requires-Python: >=3.11
License-File: LICENSE
Requires-Dist: fastapi>=0.100.0
Requires-Dist: uvicorn>=0.20.0
Requires-Dist: python-multipart
Requires-Dist: fastapi-pagination>=0.12.0
Requires-Dist: pydantic>=2.0.0
Requires-Dist: temporalio[pydantic]>=1.3.0
Requires-Dist: minio>=7.0.0
Requires-Dist: anthropic>=0.66.0
Requires-Dist: click>=0.8.0
Requires-Dist: Jinja2>=3.0.0
Requires-Dist: PyYAML>=6.0.0
Requires-Dist: python-magic>=0.4.27
Requires-Dist: multihash>=0.1.1
Requires-Dist: six>=1.16.0
Requires-Dist: jsonschema>=4.0.0
Requires-Dist: jsonpointer>=3.0.0
Provides-Extra: dev
Requires-Dist: pytest>=8.0.0; extra == "dev"
Requires-Dist: pytest-asyncio>=1.0.0; extra == "dev"
Requires-Dist: pytest-cov>=4.1.0; extra == "dev"
Requires-Dist: pytest-xdist>=3.5.0; extra == "dev"
Requires-Dist: hypothesis>=6.0.0; extra == "dev"
Requires-Dist: factory-boy>=3.2.0; extra == "dev"
Requires-Dist: mypy>=1.7.0; extra == "dev"
Requires-Dist: types-PyYAML; extra == "dev"
Requires-Dist: types-jsonschema; extra == "dev"
Requires-Dist: types-python-dateutil; extra == "dev"
Requires-Dist: black>=24.0.0; extra == "dev"
Requires-Dist: ruff>=0.5.0; extra == "dev"
Requires-Dist: pre-commit>=3.0.0; extra == "dev"
Requires-Dist: bandit; extra == "dev"
Requires-Dist: pip-tools>=7.0.0; extra == "dev"
Requires-Dist: asyncpg; extra == "dev"
Requires-Dist: sphinx>=7.0.0; extra == "dev"
Provides-Extra: docs
Requires-Dist: sphinx>=7.0.0; extra == "docs"
Requires-Dist: sphinx-autobuild>=2021.3.14; extra == "docs"
Requires-Dist: sphinx-rtd-theme>=2.0.0; extra == "docs"
Requires-Dist: furo>=2023.9.10; extra == "docs"
Requires-Dist: sphinx-autodoc-typehints>=1.25.0; extra == "docs"
Requires-Dist: sphinxcontrib-mermaid>=0.9.2; extra == "docs"
Requires-Dist: sphinxcontrib-plantuml>=0.25; extra == "docs"
Requires-Dist: sphinx-autoapi>=3.0.0; extra == "docs"
Dynamic: license-file
